rtl/memory.v
module memory(
    input  wire [7:0]       addr,
    output wire [15:0]      out
);

    reg [15:0] reg_out;
    assign out = reg_out;

    reg [15:0] memory_cell [0:255];

    initial begin
        $readmemh("/Users/sanzhar/coding/mdv/bitty/testing_tools/generator/program.txt", memory_cell);
    end
    
    always @(*) begin
        reg_out = memory_cell[addr];
    end

endmodule

rtl/branch_logic.v
module branch_logic(
    input  wire [15:0]               instruction_from_memory,
    input  wire [7:0]                current_pc,
    input  wire [15:0]               last_alu_result,
    input  wire                      instr_done,
    input  wire                      run,
    output wire [7:0]                updated_pc,
    output wire                      en_pc,
    output wire                      run_core
);

    reg        reg_run_core;
    reg  [7:0] reg_updated_pc;

    wire [1:0] instr_format              = instruction_from_memory[1:0];
    wire [1:0] branch_condition          = instruction_from_memory[3:2];
    wire [7:0] jump_branch_address       = instruction_from_memory[11:4];
    
    // just to avoid warning
    wire [3:0] empty_holder              = instruction_from_memory[15:12];
    wire _unused_holder_used             = |empty_holder;

    assign run_core                      = reg_run_core;
    assign updated_pc                    = reg_updated_pc;
    assign en_pc                         = (instr_done | ~(instr_done | run_core)) & run;

    always @(*) begin
        reg_run_core = (instr_format != 2'b10);
    end

    always @(*) begin
        if(instr_format == 2'b10) begin
            case(branch_condition)
                2'b00: begin
                    if(last_alu_result == 16'd0) begin
                        reg_updated_pc = jump_branch_address;
                    end else begin
                        reg_updated_pc = current_pc + 1;
                    end
                end
                2'b01: begin
                    if(last_alu_result == 16'd1) begin
                        reg_updated_pc = jump_branch_address;
                    end else begin
                        reg_updated_pc = current_pc + 1;
                    end
                end
                2'b10: begin
                    if(last_alu_result == 16'd2) begin
                        reg_updated_pc = jump_branch_address;
                    end else begin
                        reg_updated_pc = current_pc + 1;
                    end
                end
                default: reg_updated_pc = current_pc + 1;
            endcase
        end else begin
            reg_updated_pc = current_pc + 1;
        end
    end

endmodule

rtl/top_register.v
module top_register(
    input  wire                  clk,
    input  wire                  reset,
    input  wire                  en_i,
    input  wire [7:0]           d_in,
    output wire [7:0]           d_out
);

    reg [7:0] reg_d_out;
    assign d_out = reg_d_out;

    always @(posedge clk or posedge reset) begin
        if(reset) begin
            reg_d_out <= 8'b0;
        end else begin
            if(en_i) reg_d_out <= d_in;
        end
    end

endmodule

rtl/instr_fetch_unit.v
module instr_fetch_unit(
    input  wire             clk,
    input  wire             reset,
    input  wire             done,
    input  wire             run,
    input  wire [15:0]      last_alu_result,
    output wire             run_core,
    output wire [15:0]      instr
);
    wire                    en_pc;
    wire [7:0]              updated_pc;
    wire [7:0]              current_pc;
    wire [15:0]             memory_out;

    reg  [15:0]             instr_reg;

    assign instr          = instr_reg;

    top_register PC(
        .clk(clk),
        .reset(reset),
        .en_i(en_pc),
        .d_in(updated_pc),
        .d_out(current_pc)
    );

    branch_logic BranchLogic(
        .instruction_from_memory(memory_out),
        .current_pc(current_pc),
        .last_alu_result(last_alu_result),
        .instr_done(done),
        .run(run),
        .updated_pc(updated_pc),
        .en_pc(en_pc),
        .run_core(run_core)
    );

    memory Memory(
        .addr(current_pc),
        .out(memory_out)
    );

    always @(*) begin
        if (reset)
            instr_reg = 16'b0;
        else
            instr_reg = memory_out;
    end

endmodule

rtl/bitty_monitor.v
import "DPI-C" function void compare_results(
    input bit [15:0] instruction,
    input bit [15:0] reg0, reg1, reg2, reg3, reg4, reg5, reg6, reg7
);

module bitty_monitor (
    input wire             clk,
    input wire             done,
    input wire [15:0]      instruction,
    input wire [15:0]      reg0,
    input wire [15:0]      reg1,
    input wire [15:0]      reg2,
    input wire [15:0]      reg3,
    input wire [15:0]      reg4,
    input wire [15:0]      reg5,
    input wire [15:0]      reg6,
    input wire [15:0]      reg7
);  

    reg                    en_dpi;

    always @(posedge clk) begin
        if(done) begin
            en_dpi <= 0'b1;
        end else begin
            en_dpi <= 0'b0;
        end
    end

    always @(posedge en_dpi) begin
        compare_results(
            instruction,
            reg0, reg1, reg2, reg3,
            reg4, reg5, reg6, reg7
        );
    end

endmodule

rtl/register.v
module register(
    input  wire                  clk,
    input  wire                  reset,
    input  wire                  en_i,
    input  wire [15:0]           d_in,
    output wire [15:0]           d_out
);

    reg [15:0] reg_d_out;
    assign d_out = reg_d_out;

    always @(posedge clk or posedge reset) begin
        if(reset) begin
            reg_d_out <= 16'b0;
        end else begin
            if(en_i) reg_d_out <= d_in;
        end
    end

endmodule

rtl/alu.v
module alu(
    input  wire [15:0]               in_a,
    input  wire [15:0]               in_b,
    input  wire [2:0]                sel,
    output wire [15:0]               out
);

    reg [15:0] temp_out;
    assign out = temp_out;

    always @(*) begin
        case(sel)
            3'b000:
                temp_out = in_a + in_b;
            3'b001:
                temp_out = in_a - in_b;
            3'b010:
                temp_out = in_a & in_b;
            3'b011:
                temp_out = in_a | in_b;
            3'b100:
                temp_out = in_a ^ in_b;
            3'b101:
                temp_out = in_a << in_b % 16;
            3'b110:
                temp_out = in_a >> in_b % 16;
            3'b111: begin
                if(in_a == in_b)
                    temp_out = 16'b0;
                else if(in_a > in_b)
                    temp_out = 16'b1;
                else
                    temp_out = 16'b10;
            end
        endcase
    end


endmodule

rtl/mux.v
module mux(
    input  wire [3:0]        sel,
    input  wire [15:0]       reg_0,
    input  wire [15:0]       reg_1,
    input  wire [15:0]       reg_2,
    input  wire [15:0]       reg_3,
    input  wire [15:0]       reg_4,
    input  wire [15:0]       reg_5,
    input  wire [15:0]       reg_6,
    input  wire [15:0]       reg_7,
    input  wire [15:0]       reg_8,
    input  wire [15:0]       reg_9,
    output wire [15:0]       out
);

    reg [15:0] reg_out;
    assign out = reg_out;

    always @(*) begin
        case(sel)
            4'b0000:
                reg_out = reg_0;
            4'b0001:
                reg_out = reg_1;
            4'b0010:
                reg_out = reg_2;
            4'b0011:
                reg_out = reg_3;
            4'b0100:
                reg_out = reg_4;
            4'b0101:
                reg_out = reg_5;
            4'b0110:
                reg_out = reg_6;
            4'b0111:
                reg_out = reg_7;
            4'b1000:
                reg_out = reg_8;
            4'b1001:
                reg_out = reg_9;
            default:
                reg_out = 16'b0;
        endcase
    end

endmodule

rtl/control_unit.v
module control_unit(
    input  wire             clk,
    input  wire             reset,
    input  wire             run,
    input  wire [15:0]      d_in,
    output wire             done,
    output wire             en_s,
    output wire             en_c,
    output wire             en_0,
    output wire             en_1,
    output wire             en_2,
    output wire             en_3,
    output wire             en_4,
    output wire             en_5,
    output wire             en_6,
    output wire             en_7,
    output wire             en_i,
    output wire [2:0]       alu_sel,
    output wire [3:0]       mux_sel,
    output wire [15:0]      imm_val
);

    reg              reg_done;
    reg              reg_en_s;
    reg              reg_en_c;
    reg              reg_en_0;
    reg              reg_en_1;
    reg              reg_en_2;
    reg              reg_en_3;
    reg              reg_en_4;
    reg              reg_en_5;
    reg              reg_en_6;
    reg              reg_en_7;
    reg              reg_en_i;
    reg [2:0]        reg_alu_sel;
    reg [3:0]        reg_mux_sel;
    reg [15:0]       reg_imm_val;

    assign done    = reg_done;
    assign en_s    = reg_en_s;
    assign en_c    = reg_en_c;
    assign en_0    = reg_en_0;
    assign en_1    = reg_en_1;
    assign en_2    = reg_en_2;
    assign en_3    = reg_en_3;
    assign en_4    = reg_en_4;
    assign en_5    = reg_en_5;
    assign en_6    = reg_en_6;
    assign en_7    = reg_en_7;
    assign en_i    = reg_en_i;
    assign alu_sel = reg_alu_sel;
    assign mux_sel = reg_mux_sel;
    assign imm_val = reg_imm_val;

    parameter INITIAL_STATE     = 2'b00;
    parameter LOAD_STATE        = 2'b01;
    parameter CALCULATE_STATE   = 2'b10;
    parameter STORE_STATE       = 2'b11;

    parameter R_TYPE_INST       = 2'b00;
    parameter I_TYPE_INST       = 2'b01;

    reg [1:0] current_state, next_state;

    wire [1:0] inst_format = d_in[1:0];
    wire [2:0] alu_selection = d_in[4:2];
    wire [2:0] first_operand = d_in[15:13];

    // R_TYPE
    wire [2:0] second_operand = d_in[12:10];

    // I_TYPE
    wire [7:0] immediate_val  = d_in[12:5];

    always @(posedge clk or posedge reset) begin
        if(reset)
            current_state <= INITIAL_STATE;
        else if(run) begin
            current_state <= next_state;
        end
    end

    always @(*) begin
        case(current_state)
            INITIAL_STATE:   next_state = LOAD_STATE;
            LOAD_STATE:      next_state = CALCULATE_STATE;
            CALCULATE_STATE: next_state = STORE_STATE;
            STORE_STATE:     next_state = INITIAL_STATE;
            default:         next_state = INITIAL_STATE;
        endcase
    end

    always @(*) begin

        reg_done = 1'b0;
        reg_en_s = 1'b0;
        reg_en_c = 1'b0;
        reg_en_0 = 1'b0;
        reg_en_1 = 1'b0;
        reg_en_2 = 1'b0;
        reg_en_3 = 1'b0;
        reg_en_4 = 1'b0;
        reg_en_5 = 1'b0;
        reg_en_6 = 1'b0;
        reg_en_7 = 1'b0;
        reg_en_i = 1'b0;
        reg_alu_sel = 3'b000;
        reg_mux_sel = 4'b0000;

        if(!reset && run) begin
            case(current_state)
                INITIAL_STATE: begin
                    reg_en_i    = 1'b1;
                end
                LOAD_STATE: begin
                    reg_mux_sel = {1'b0, first_operand};
                    reg_en_s    = 1'b1;
                end
                CALCULATE_STATE: begin
                    case(inst_format)
                        R_TYPE_INST: begin
                            reg_mux_sel = {1'b0, second_operand};
                            reg_en_c    = 1'b1; 
                            reg_alu_sel = alu_selection[2:0];
                        end
                        I_TYPE_INST: begin
                            reg_mux_sel = {4'b1000};
                            reg_imm_val = {{8{immediate_val[7]}}, immediate_val};
                            reg_en_c    = 1'b1;
                            reg_alu_sel = alu_selection[2:0];
                        end
                        default: begin
                            reg_mux_sel = {1'b0, second_operand};
                            reg_en_c    = 1'b1; 
                            reg_alu_sel = alu_selection[2:0];
                        end
                    endcase
                end
                STORE_STATE: begin
                    case(first_operand)
                        3'b000: reg_en_0 = 1'b1;
                        3'b001: reg_en_1 = 1'b1;
                        3'b010: reg_en_2 = 1'b1;
                        3'b011: reg_en_3 = 1'b1;
                        3'b100: reg_en_4 = 1'b1;
                        3'b101: reg_en_5 = 1'b1;
                        3'b110: reg_en_6 = 1'b1;
                        3'b111: reg_en_7 = 1'b1;
                    endcase
                    reg_done = 1'b1;
                end
                default: begin
                    reg_done = 1'b0;
                    reg_en_s = 1'b0;
                    reg_en_c = 1'b0;
                    reg_en_0 = 1'b0;
                    reg_en_1 = 1'b0;
                    reg_en_2 = 1'b0;
                    reg_en_3 = 1'b0;
                    reg_en_4 = 1'b0;
                    reg_en_5 = 1'b0;
                    reg_en_6 = 1'b0;
                    reg_en_7 = 1'b0;
                    reg_en_i = 1'b0;
                    reg_alu_sel = 3'b000;
                    reg_mux_sel = 4'b0000;
                end
            endcase
        end
    end

endmodule

rtl/bitty_core.v
module bitty_core (
    input  wire              clk,
    input  wire              reset,
    input  wire              run,
    input  wire [15:0]       instruction,
    output wire              done,
    output wire [15:0]       last_alu_result
);

    wire                     en_s;
    wire                     en_c;
    wire                     en_0;
    wire                     en_1;
    wire                     en_2;
    wire                     en_3;
    wire                     en_4;
    wire                     en_5;
    wire                     en_6;
    wire                     en_7;
    wire                     en_i;

    wire [15:0]              reg_inst_to_control_unit;
    wire [2:0]               control_unit_to_alu_sel;
    wire [3:0]               control_unit_to_mux_sel;
    wire [15:0]              control_unit_to_mux_imm_val;

    wire [15:0]              reg_c_to_regs;
    wire [15:0]              reg0_to_mux;
    wire [15:0]              reg1_to_mux;
    wire [15:0]              reg2_to_mux;
    wire [15:0]              reg3_to_mux;
    wire [15:0]              reg4_to_mux;
    wire [15:0]              reg5_to_mux;
    wire [15:0]              reg6_to_mux;
    wire [15:0]              reg7_to_mux;
    wire [15:0]              mux_out;

    wire [15:0]              reg_s_to_alu;
    wire [15:0]              alu_to_reg_c;

    assign last_alu_result = reg_c_to_regs;

    register RegInst(
        .clk(clk),
        .reset(reset),
        .en_i(en_i),
        .d_in(instruction),
        .d_out(reg_inst_to_control_unit)
    );

    register Reg0(
        .clk(clk),
        .reset(reset),
        .en_i(en_0),
        .d_in(reg_c_to_regs),
        .d_out(reg0_to_mux)
    );

    register Reg1(
        .clk(clk),
        .reset(reset),
        .en_i(en_1),
        .d_in(reg_c_to_regs),
        .d_out(reg1_to_mux)
    );

    register Reg2(
        .clk(clk),
        .reset(reset),
        .en_i(en_2),
        .d_in(reg_c_to_regs),
        .d_out(reg2_to_mux)
    );

    register Reg3(
        .clk(clk),
        .reset(reset),
        .en_i(en_3),
        .d_in(reg_c_to_regs),
        .d_out(reg3_to_mux)
    );

    register Reg4(
        .clk(clk),
        .reset(reset),
        .en_i(en_4),
        .d_in(reg_c_to_regs),
        .d_out(reg4_to_mux)
    );

    register Reg5(
        .clk(clk),
        .reset(reset),
        .en_i(en_5),
        .d_in(reg_c_to_regs),
        .d_out(reg5_to_mux)
    );

    register Reg6(
        .clk(clk),
        .reset(reset),
        .en_i(en_6),
        .d_in(reg_c_to_regs),
        .d_out(reg6_to_mux)
    );

    register Reg7(
        .clk(clk),
        .reset(reset),
        .en_i(en_7),
        .d_in(reg_c_to_regs),
        .d_out(reg7_to_mux)
    );

    control_unit ControlUnit(
        .clk(clk),
        .reset(reset),
        .run(run),
        .d_in(reg_inst_to_control_unit),
        .done(done),
        .en_s(en_s),
        .en_c(en_c),
        .en_0(en_0),
        .en_1(en_1),
        .en_2(en_2),
        .en_3(en_3),
        .en_4(en_4),
        .en_5(en_5),
        .en_6(en_6),
        .en_7(en_7),
        .en_i(en_i),
        .alu_sel(control_unit_to_alu_sel),
        .mux_sel(control_unit_to_mux_sel),
        .imm_val(control_unit_to_mux_imm_val)
    );

    mux Mux(
        .sel(control_unit_to_mux_sel),
        .reg_0(reg0_to_mux),
        .reg_1(reg1_to_mux),
        .reg_2(reg2_to_mux),
        .reg_3(reg3_to_mux),
        .reg_4(reg4_to_mux),
        .reg_5(reg5_to_mux),
        .reg_6(reg6_to_mux),
        .reg_7(reg7_to_mux),
        .reg_8(control_unit_to_mux_imm_val),
        .reg_9(16'b0),
        .out(mux_out)
    );

    register RegS(
        .clk(clk),
        .reset(reset),
        .en_i(en_s),
        .d_in(mux_out),
        .d_out(reg_s_to_alu)
    );

    alu Alu(
        .in_a(reg_s_to_alu),
        .in_b(mux_out),
        .sel(control_unit_to_alu_sel),
        .out(alu_to_reg_c)
    );

    register RegC(
        .clk(clk),
        .reset(reset),
        .en_i(en_c),
        .d_in(alu_to_reg_c),
        .d_out(reg_c_to_regs)
    );

    bitty_monitor Monitor(
        .clk(clk),
        .done(done),
        .instruction(reg_inst_to_control_unit),
        .reg0(reg0_to_mux),
        .reg1(reg1_to_mux),
        .reg2(reg2_to_mux),
        .reg3(reg3_to_mux),
        .reg4(reg4_to_mux),
        .reg5(reg5_to_mux),
        .reg6(reg6_to_mux),
        .reg7(reg7_to_mux)
    );

endmodule

rtl/top.v
module top(
    input  wire             clk,
    input  wire             reset,
    input  wire             run
);

    wire                    instr_done;
    wire                    run_core;
    wire [15:0]             instr;
    wire [15:0]             last_alu_result;

    bitty_core Core(
        .clk(clk),
        .reset(reset),
        .run(run_core),
        .instruction(instr),
        .done(instr_done),
        .last_alu_result(last_alu_result)
    );

    instr_fetch_unit InstrFetchUnit(
        .clk(clk),
        .reset(reset),
        .done(instr_done),
        .run(run),
        .last_alu_result(last_alu_result),
        .run_core(run_core),
        .instr(instr)
    );

endmodule

dump.vcd
$version Generated by VerilatedVcd $end
$timescale 1ps $end
 $scope module TOP $end
  $var wire 1 N clk $end
  $var wire 1 O reset $end
  $var wire 1 P run $end
  $scope module top $end
   $var wire 1 N clk $end
   $var wire 1 O reset $end
   $var wire 1 P run $end
   $var wire 1 # instr_done $end
   $var wire 1 4 run_core $end
   $var wire 16 Q instr [15:0] $end
   $var wire 16 5 last_alu_result [15:0] $end
   $scope module Core $end
    $var wire 1 N clk $end
    $var wire 1 O reset $end
    $var wire 1 4 run $end
    $var wire 16 Q instruction [15:0] $end
    $var wire 1 # done $end
    $var wire 16 5 last_alu_result [15:0] $end
    $var wire 1 $ en_s $end
    $var wire 1 % en_c $end
    $var wire 1 & en_0 $end
    $var wire 1 ' en_1 $end
    $var wire 1 ( en_2 $end
    $var wire 1 ) en_3 $end
    $var wire 1 * en_4 $end
    $var wire 1 + en_5 $end
    $var wire 1 , en_6 $end
    $var wire 1 - en_7 $end
    $var wire 1 . en_i $end
    $var wire 16 6 reg_inst_to_control_unit [15:0] $end
    $var wire 3 / control_unit_to_alu_sel [2:0] $end
    $var wire 4 0 control_unit_to_mux_sel [3:0] $end
    $var wire 16 1 control_unit_to_mux_imm_val [15:0] $end
    $var wire 16 5 reg_c_to_regs [15:0] $end
    $var wire 16 7 reg0_to_mux [15:0] $end
    $var wire 16 8 reg1_to_mux [15:0] $end
    $var wire 16 9 reg2_to_mux [15:0] $end
    $var wire 16 : reg3_to_mux [15:0] $end
    $var wire 16 ; reg4_to_mux [15:0] $end
    $var wire 16 < reg5_to_mux [15:0] $end
    $var wire 16 = reg6_to_mux [15:0] $end
    $var wire 16 > reg7_to_mux [15:0] $end
    $var wire 16 2 mux_out [15:0] $end
    $var wire 16 ? reg_s_to_alu [15:0] $end
    $var wire 16 3 alu_to_reg_c [15:0] $end
    $scope module Alu $end
     $var wire 16 ? in_a [15:0] $end
     $var wire 16 2 in_b [15:0] $end
     $var wire 3 / sel [2:0] $end
     $var wire 16 3 out [15:0] $end
     $var wire 16 3 temp_out [15:0] $end
    $upscope $end
    $scope module ControlUnit $end
     $var wire 1 N clk $end
     $var wire 1 O reset $end
     $var wire 1 4 run $end
     $var wire 16 6 d_in [15:0] $end
     $var wire 1 # done $end
     $var wire 1 $ en_s $end
     $var wire 1 % en_c $end
     $var wire 1 & en_0 $end
     $var wire 1 ' en_1 $end
     $var wire 1 ( en_2 $end
     $var wire 1 ) en_3 $end
     $var wire 1 * en_4 $end
     $var wire 1 + en_5 $end
     $var wire 1 , en_6 $end
     $var wire 1 - en_7 $end
     $var wire 1 . en_i $end
     $var wire 3 / alu_sel [2:0] $end
     $var wire 4 0 mux_sel [3:0] $end
     $var wire 16 1 imm_val [15:0] $end
     $var wire 1 # reg_done $end
     $var wire 1 $ reg_en_s $end
     $var wire 1 % reg_en_c $end
     $var wire 1 & reg_en_0 $end
     $var wire 1 ' reg_en_1 $end
     $var wire 1 ( reg_en_2 $end
     $var wire 1 ) reg_en_3 $end
     $var wire 1 * reg_en_4 $end
     $var wire 1 + reg_en_5 $end
     $var wire 1 , reg_en_6 $end
     $var wire 1 - reg_en_7 $end
     $var wire 1 . reg_en_i $end
     $var wire 3 / reg_alu_sel [2:0] $end
     $var wire 4 0 reg_mux_sel [3:0] $end
     $var wire 16 1 reg_imm_val [15:0] $end
     $var wire 2 T INITIAL_STATE [1:0] $end
     $var wire 2 U LOAD_STATE [1:0] $end
     $var wire 2 V CALCULATE_STATE [1:0] $end
     $var wire 2 W STORE_STATE [1:0] $end
     $var wire 2 T R_TYPE_INST [1:0] $end
     $var wire 2 U I_TYPE_INST [1:0] $end
     $var wire 2 @ current_state [1:0] $end
     $var wire 2 A next_state [1:0] $end
     $var wire 2 B inst_format [1:0] $end
     $var wire 3 C alu_selection [2:0] $end
     $var wire 3 D first_operand [2:0] $end
     $var wire 3 E second_operand [2:0] $end
     $var wire 8 F immediate_val [7:0] $end
    $upscope $end
    $scope module Monitor $end
     $var wire 1 N clk $end
     $var wire 1 # done $end
     $var wire 16 6 instruction [15:0] $end
     $var wire 16 7 reg0 [15:0] $end
     $var wire 16 8 reg1 [15:0] $end
     $var wire 16 9 reg2 [15:0] $end
     $var wire 16 : reg3 [15:0] $end
     $var wire 16 ; reg4 [15:0] $end
     $var wire 16 < reg5 [15:0] $end
     $var wire 16 = reg6 [15:0] $end
     $var wire 16 > reg7 [15:0] $end
     $var wire 1 R en_dpi $end
    $upscope $end
    $scope module Mux $end
     $var wire 4 0 sel [3:0] $end
     $var wire 16 7 reg_0 [15:0] $end
     $var wire 16 8 reg_1 [15:0] $end
     $var wire 16 9 reg_2 [15:0] $end
     $var wire 16 : reg_3 [15:0] $end
     $var wire 16 ; reg_4 [15:0] $end
     $var wire 16 < reg_5 [15:0] $end
     $var wire 16 = reg_6 [15:0] $end
     $var wire 16 > reg_7 [15:0] $end
     $var wire 16 1 reg_8 [15:0] $end
     $var wire 16 X reg_9 [15:0] $end
     $var wire 16 2 out [15:0] $end
     $var wire 16 2 reg_out [15:0] $end
    $upscope $end
    $scope module Reg0 $end
     $var wire 1 N clk $end
     $var wire 1 O reset $end
     $var wire 1 & en_i $end
     $var wire 16 5 d_in [15:0] $end
     $var wire 16 7 d_out [15:0] $end
     $var wire 16 7 reg_d_out [15:0] $end
    $upscope $end
    $scope module Reg1 $end
     $var wire 1 N clk $end
     $var wire 1 O reset $end
     $var wire 1 ' en_i $end
     $var wire 16 5 d_in [15:0] $end
     $var wire 16 8 d_out [15:0] $end
     $var wire 16 8 reg_d_out [15:0] $end
    $upscope $end
    $scope module Reg2 $end
     $var wire 1 N clk $end
     $var wire 1 O reset $end
     $var wire 1 ( en_i $end
     $var wire 16 5 d_in [15:0] $end
     $var wire 16 9 d_out [15:0] $end
     $var wire 16 9 reg_d_out [15:0] $end
    $upscope $end
    $scope module Reg3 $end
     $var wire 1 N clk $end
     $var wire 1 O reset $end
     $var wire 1 ) en_i $end
     $var wire 16 5 d_in [15:0] $end
     $var wire 16 : d_out [15:0] $end
     $var wire 16 : reg_d_out [15:0] $end
    $upscope $end
    $scope module Reg4 $end
     $var wire 1 N clk $end
     $var wire 1 O reset $end
     $var wire 1 * en_i $end
     $var wire 16 5 d_in [15:0] $end
     $var wire 16 ; d_out [15:0] $end
     $var wire 16 ; reg_d_out [15:0] $end
    $upscope $end
    $scope module Reg5 $end
     $var wire 1 N clk $end
     $var wire 1 O reset $end
     $var wire 1 + en_i $end
     $var wire 16 5 d_in [15:0] $end
     $var wire 16 < d_out [15:0] $end
     $var wire 16 < reg_d_out [15:0] $end
    $upscope $end
    $scope module Reg6 $end
     $var wire 1 N clk $end
     $var wire 1 O reset $end
     $var wire 1 , en_i $end
     $var wire 16 5 d_in [15:0] $end
     $var wire 16 = d_out [15:0] $end
     $var wire 16 = reg_d_out [15:0] $end
    $upscope $end
    $scope module Reg7 $end
     $var wire 1 N clk $end
     $var wire 1 O reset $end
     $var wire 1 - en_i $end
     $var wire 16 5 d_in [15:0] $end
     $var wire 16 > d_out [15:0] $end
     $var wire 16 > reg_d_out [15:0] $end
    $upscope $end
    $scope module RegC $end
     $var wire 1 N clk $end
     $var wire 1 O reset $end
     $var wire 1 % en_i $end
     $var wire 16 3 d_in [15:0] $end
     $var wire 16 5 d_out [15:0] $end
     $var wire 16 5 reg_d_out [15:0] $end
    $upscope $end
    $scope module RegInst $end
     $var wire 1 N clk $end
     $var wire 1 O reset $end
     $var wire 1 . en_i $end
     $var wire 16 Q d_in [15:0] $end
     $var wire 16 6 d_out [15:0] $end
     $var wire 16 6 reg_d_out [15:0] $end
    $upscope $end
    $scope module RegS $end
     $var wire 1 N clk $end
     $var wire 1 O reset $end
     $var wire 1 $ en_i $end
     $var wire 16 2 d_in [15:0] $end
     $var wire 16 ? d_out [15:0] $end
     $var wire 16 ? reg_d_out [15:0] $end
    $upscope $end
   $upscope $end
   $scope module InstrFetchUnit $end
    $var wire 1 N clk $end
    $var wire 1 O reset $end
    $var wire 1 # done $end
    $var wire 1 P run $end
    $var wire 16 5 last_alu_result [15:0] $end
    $var wire 1 4 run_core $end
    $var wire 16 Q instr [15:0] $end
    $var wire 1 S en_pc $end
    $var wire 8 G updated_pc [7:0] $end
    $var wire 8 H current_pc [7:0] $end
    $var wire 16 I memory_out [15:0] $end
    $var wire 16 Q instr_reg [15:0] $end
    $scope module BranchLogic $end
     $var wire 16 I instruction_from_memory [15:0] $end
     $var wire 8 H current_pc [7:0] $end
     $var wire 16 5 last_alu_result [15:0] $end
     $var wire 1 # instr_done $end
     $var wire 1 P run $end
     $var wire 8 G updated_pc [7:0] $end
     $var wire 1 S en_pc $end
     $var wire 1 4 run_core $end
     $var wire 1 4 reg_run_core $end
     $var wire 8 G reg_updated_pc [7:0] $end
     $var wire 2 J instr_format [1:0] $end
     $var wire 2 K branch_condition [1:0] $end
     $var wire 8 L jump_branch_address [7:0] $end
     $var wire 4 M empty_holder [3:0] $end
    $upscope $end
    $scope module Memory $end
     $var wire 8 H addr [7:0] $end
     $var wire 16 I out [15:0] $end
     $var wire 16 I reg_out [15:0] $end
    $upscope $end
    $scope module PC $end
     $var wire 1 N clk $end
     $var wire 1 O reset $end
     $var wire 1 S en_i $end
     $var wire 8 G d_in [7:0] $end
     $var wire 8 H d_out [7:0] $end
     $var wire 8 H reg_d_out [7:0] $end
    $upscope $end
   $upscope $end
  $upscope $end
 $upscope $end
$enddefinitions $end


#0
0#
0$
0%
0&
0'
0(
0)
0*
0+
0,
0-
0.
b000 /
b0000 0
b0000000000000000 1
b0000000000000000 2
b0000000000000000 3
14
b0000000000000000 5
b0000000000000000 6
b0000000000000000 7
b0000000000000000 8
b0000000000000000 9
b0000000000000000 :
b0000000000000000 ;
b0000000000000000 <
b0000000000000000 =
b0000000000000000 >
b0000000000000000 ?
b00 @
b01 A
b00 B
b000 C
b000 D
b000 E
b00000000 F
b00000001 G
b00000000 H
b0101000001000101 I
b01 J
b01 K
b00000100 L
b0101 M
0N
1O
0P
b0000000000000000 Q
0R
0S
b00 T
b01 U
b10 V
b11 W
b0000000000000000 X
#1
1N
#2
0N
#3
1N
#4
0N
#5
1N
#6
0N
#7
1N
#8
0N
#9
1N
#10
1.
0N
0O
1P
b0101000001000101 Q
#11
1$
0.
b0010 0
b0101000001000101 6
b01 @
b10 A
b01 B
b001 C
b010 D
b100 E
b10000010 F
1N
#12
0N
#13
0$
1%
b001 /
b1000 0
b1111111110000010 1
b1111111110000010 2
b0000000001111110 3
b10 @
b11 A
1N
#14
0N
#15
1#
0%
1(
b000 /
b0000 0
b0000000000000000 2
b0000000000000000 3
b0000000001111110 5
b11 @
b00 A
1N
1S
#16
0N
#17
0#
0(
04
b0000000001111110 9
b00 @
b01 A
b00000010 G
b00000001 H
b0000010000111010 I
b10 J
b10 K
b01000011 L
b0000 M
1N
b0000010000111010 Q
1R
#18
0N
#19
1.
14
b00000011 G
b00000010 H
b1000100000010100 I
b00 J
b01 K
b10000001 L
b1000 M
1N
b1000100000010100 Q
0R
0S
#20
0N
#21
1$
0.
b0100 0
b1000100000010100 6
b01 @
b10 A
b00 B
b101 C
b100 D
b010 E
b01000000 F
1N
#22
0N
#23
0$
1%
b101 /
b0010 0
b0000000001111110 2
b10 @
b11 A
1N
#24
0N
#25
1#
0%
1*
b000 /
b0000 0
b0000000000000000 2
b0000000000000000 5
b11 @
b00 A
1N
1S
#26
0N
#27
0#
0*
1.
b00 @
b01 A
b00000100 G
b00000011 H
b0011001100011101 I
b01 J
b11 K
b00110001 L
b0011 M
1N
b0011001100011101 Q
1R
0S
#28
0N
#29
1$
0.
b0001 0
b0011001100011101 6
b01 @
b10 A
b01 B
b111 C
b001 D
b100 E
b10011000 F
1N
0R
#30
0N
#31
0$
1%
b111 /
b1000 0
b1111111110011000 1
b1111111110011000 2
b0000000000000010 3
b10 @
b11 A
1N
#32
0N
#33
1#
0%
1'
b000 /
b0000 0
b0000000000000000 2
b0000000000000000 3
b0000000000000010 5
b11 @
b00 A
1N
1S
#34
0N
#35
0#
0'
1.
b0000000000000010 8
b00 @
b01 A
b00000101 G
b00000100 H
b1010000010100101 I
b01 K
b00001010 L
b1010 M
1N
b1010000010100101 Q
1R
0S
#36
0N
#37
1$
0.
b0101 0
b1010000010100101 6
b01 @
b10 A
b001 C
b101 D
b000 E
b00000101 F
1N
0R
#38
0N
#39
0$
1%
b001 /
b1000 0
b0000000000000101 1
b0000000000000101 2
b1111111111111011 3
b10 @
b11 A
1N
#40
0N
#41
1#
0%
1+
b000 /
b0000 0
b0000000000000000 2
b0000000000000000 3
b1111111111111011 5
b11 @
b00 A
1N
1S
#42
0N
#43
0#
0+
1.
b1111111111111011 <
b00 @
b01 A
b00000110 G
b00000101 H
b1101000100001101 I
b11 K
b00010000 L
b1101 M
1N
b1101000100001101 Q
1R
0S
#44
0N
#45
1$
0.
b0110 0
b1101000100001101 6
b01 @
b10 A
b011 C
b110 D
b100 E
b10001000 F
1N
0R
#46
0N
#47
0$
1%
b011 /
b1000 0
b1111111110001000 1
b1111111110001000 2
b1111111110001000 3
b10 @
b11 A
1N
#48
0N
#49
1#
0%
1,
b000 /
b0000 0
b0000000000000000 2
b0000000000000000 3
b1111111110001000 5
b11 @
b00 A
1N
1S
#50
0N
#51
0#
0,
1.
b1111111110001000 =
b00 @
b01 A
b00000111 G
b00000110 H
b0000011001101001 I
b10 K
b01100110 L
b0000 M
1N
b0000011001101001 Q
1R
0S
#52
0N
#53
1$
0.
b0000011001101001 6
b01 @
b10 A
b010 C
b000 D
b001 E
b00110011 F
1N
0R
#54
0N
#55
0$
1%
b010 /
b1000 0
b0000000000110011 1
b0000000000110011 2
b10 @
b11 A
1N
#56
0N
#57
1#
0%
1&
b000 /
b0000 0
b0000000000000000 2
b0000000000000000 5
b11 @
b00 A
1N
1S
#58
0N
#59
0#
0&
04
b00 @
b01 A
b00001000 G
b00000111 H
b0000000011010110 I
b10 J
b01 K
b00001101 L
1N
b0000000011010110 Q
1R
#60
0N
#61
1.
14
b00001001 G
b00001000 H
b0001101000111101 I
b01 J
b11 K
b10100011 L
b0001 M
1N
b0001101000111101 Q
0R
0S
#62
0N
#63
1$
0.
b0001101000111101 6
b01 @
b10 A
b111 C
b110 E
b11010001 F
1N
#64
0N
#65
0$
1%
b111 /
b1000 0
b1111111111010001 1
b1111111111010001 2
b0000000000000010 3
b10 @
b11 A
1N
#66
0N
